odoo/addons/base_ebill_payment_contract/README.rst
odoo/addons/base_ebill_payment_contract/__init__.py
odoo/addons/base_ebill_payment_contract/__manifest__.py
odoo/addons/base_ebill_payment_contract/demo/ebill_payment_contract.xml
odoo/addons/base_ebill_payment_contract/i18n/base_ebill_payment_contract.pot
odoo/addons/base_ebill_payment_contract/i18n/es.po
odoo/addons/base_ebill_payment_contract/i18n/it.po
odoo/addons/base_ebill_payment_contract/models/__init__.py
odoo/addons/base_ebill_payment_contract/models/ebill_payment_contract.py
odoo/addons/base_ebill_payment_contract/models/res_partner.py
odoo/addons/base_ebill_payment_contract/readme/CONTRIBUTORS.md
odoo/addons/base_ebill_payment_contract/readme/CREDITS.md
odoo/addons/base_ebill_payment_contract/readme/DESCRIPTION.md
odoo/addons/base_ebill_payment_contract/readme/USAGE.md
odoo/addons/base_ebill_payment_contract/security/ir.model.access.csv
odoo/addons/base_ebill_payment_contract/static/description/icon.png
odoo/addons/base_ebill_payment_contract/static/description/index.html
odoo/addons/base_ebill_payment_contract/tests/__init__.py
odoo/addons/base_ebill_payment_contract/tests/test_base_ebill_payment_contract.py
odoo/addons/base_ebill_payment_contract/views/ebill_payment_contract.xml
odoo_addon_base_ebill_payment_contract-18.0.1.0.0.2.dist-info/METADATA
odoo_addon_base_ebill_payment_contract-18.0.1.0.0.2.dist-info/WHEEL
odoo_addon_base_ebill_payment_contract-18.0.1.0.0.2.dist-info/top_level.txt
odoo_addon_base_ebill_payment_contract-18.0.1.0.0.2.dist-info/RECORD
